README.md
setup.py
co6co.sanic_ext.egg-info/PKG-INFO
co6co.sanic_ext.egg-info/SOURCES.txt
co6co.sanic_ext.egg-info/dependency_links.txt
co6co.sanic_ext.egg-info/requires.txt
co6co.sanic_ext.egg-info/top_level.txt
co6co.sanic_ext.egg-info/zip-safe
co6co_sanic_ext/__init__.py
co6co_sanic_ext/sanics.py
co6co_sanic_ext/session.py
co6co_sanic_ext/api/__init__.py
co6co_sanic_ext/cors/__init__.py
co6co_sanic_ext/cors/core.py
co6co_sanic_ext/cors/decorator.py
co6co_sanic_ext/cors/extension.py
co6co_sanic_ext/cors/version.py
co6co_sanic_ext/model/__init__.py
co6co_sanic_ext/model/res/__init__.py
co6co_sanic_ext/model/res/result.py
co6co_sanic_ext/utils/__init__.py
co6co_sanic_ext/utils/cors_utils.py
co6co_sanic_ext/view_model/__init__.py