Metadata-Version: 2.1
Name: co6co.sanic-ext
Version: 0.0.13
Summary: web 扩展
Home-page: http://github.com/co6co
Author: co6co
Author-email: co6co@qq.com
Classifier: Programming Language :: Python :: 3
Classifier: Programming Language :: Python :: 3.6
Requires-Dist: co6co>=0.0.24
Requires-Dist: co6co.web-session>=0.0.1
